.gitignore
.gitmodules
CHANGES.txt
CONTRIBUTORS.txt
COPYRIGHT.txt
LICENSE.txt
MANIFEST.in
README.rst
rtd.txt
setup.cfg
setup.py
tox.ini
docs/Makefile
docs/_themes
docs/api.rst
docs/conf.py
docs/glossary.rst
docs/index.rst
docs/overview.rst
jslibs/__init__.py
jslibs/jslibs.pt
jslibs/jslibs_prepare_sources.py
jslibs/juice_jslibs.py
jslibs/pyramid_support.py
jslibs/tests.py
jslibs.egg-info/PKG-INFO
jslibs.egg-info/SOURCES.txt
jslibs.egg-info/dependency_links.txt
jslibs.egg-info/entry_points.txt
jslibs.egg-info/not-zip-safe
jslibs.egg-info/requires.txt
jslibs.egg-info/top_level.txt
jslibs/externals/git_submodules_go_here
jslibs/externals/bottlecap-extras/bottlecap-head-0-jquery-1.6.2.js
jslibs/externals/bottlecap-extras/bottlecap-tail-0.js
jslibs/externals/bottlecap-extras/0/modernizr-2.0.6.min.js
jslibs/externals/bottlecap-extras/0/mustache-0.3.0.js
jslibs/externals/bottlecap-extras/0/respond.min.js
jslibs/externals/jquery/1.6.2
jslibs/externals/jquery/jquery-1.6.2.js
jslibs/externals/jquery-ui/1.9m5
jslibs/externals/jquery-ui/jquery-1.6.2-jquery-ui-1.9m5.js
jslibs/externals/jquery-ui/jquery-ui-1.9m5-smoothness.css
jslibs/externals/jquery-ui/jquery-ui-1.9m5-unthemed.css
jslibs/externals/jquery-ui/jquery-ui-1.9m5.js
jslibs/externals/jquery-ui/jquery-ui-theme-smoothness.css
jslibs/externals/jquery-ui/1.9m5-extras/jquery.ui.selectmenu.css
jslibs/externals/jquery-ui/1.9m5-extras/jquery.ui.selectmenu.js
jslibs/externals/jquery-ui/themes/smoothness/jquery.ui.theme.css
jslibs/externals/jquery-ui/themes/smoothness/images/ui-bg_flat_0_aaaaaa_40x100.png
jslibs/externals/jquery-ui/themes/smoothness/images/ui-bg_flat_75_ffffff_40x100.png
jslibs/externals/jquery-ui/themes/smoothness/images/ui-bg_glass_55_fbf9ee_1x400.png
jslibs/externals/jquery-ui/themes/smoothness/images/ui-bg_glass_65_ffffff_1x400.png
jslibs/externals/jquery-ui/themes/smoothness/images/ui-bg_glass_75_dadada_1x400.png
jslibs/externals/jquery-ui/themes/smoothness/images/ui-bg_glass_75_e6e6e6_1x400.png
jslibs/externals/jquery-ui/themes/smoothness/images/ui-bg_glass_95_fef1ec_1x400.png
jslibs/externals/jquery-ui/themes/smoothness/images/ui-bg_highlight-soft_75_cccccc_1x100.png
