Metadata-Version: 1.0
Name: jslibs
Version: 0.10
Summary: A package which does stuff with js libs
Home-page: http://docs.pylonsproject.org
Author: Pylons Project Contributors
Author-email: pylons-devel@googlegroups.com
License: BSD-derived (http://www.repoze.org/LICENSE.txt)
Keywords: wsgi pylons pyramid
Platform: UNKNOWN
Classifier: Intended Audience :: Developers
Classifier: Programming Language :: Python
Classifier: Programming Language :: JavaScript
Classifier: Framework :: Pylons
Classifier: Topic :: Internet :: WWW/HTTP :: WSGI
Classifier: License :: Repoze Public License
